proceduralSettingsWidget/__init__.py
proceduralSettingsWidget/inputWidgets.py
proceduralSettingsWidget/parameters.py
proceduralSettingsWidget/settingsWidget.py
proceduralSettingsWidget/version.py
proceduralSettingsWidget-0.0.1.dist-info/LICENSE
proceduralSettingsWidget-0.0.1.dist-info/METADATA
proceduralSettingsWidget-0.0.1.dist-info/WHEEL
proceduralSettingsWidget-0.0.1.dist-info/top_level.txt
proceduralSettingsWidget-0.0.1.dist-info/RECORD
