Metadata-Version: 2.1
Name: proceduralSettingsWidget
Version: 0.0.1
Summary: A widget to display and edit settings procedurally.
Author-email: Gabe Reed <gabrieljreed@gmail.com>
License: MIT License
Project-URL: Homepage, https://github.com/gabrieljreed/ProceduralSettingsWidget
Project-URL: Bug Tracker, https://github.com/gabrieljreed/ProceduralSettingsWidget/issues
Keywords: settings,procedural,widget,qt,pyside2,pyqt
Requires-Python: >=3.6
License-File: LICENSE
Requires-Dist: PySide2
